cudf_polars/GIT_COMMIT
cudf_polars/VERSION
cudf_polars/__init__.py
cudf_polars/_version.py
cudf_polars/callback.py
cudf_polars/py.typed
cudf_polars/containers/__init__.py
cudf_polars/containers/column.py
cudf_polars/containers/dataframe.py
cudf_polars/containers/datatype.py
cudf_polars/dsl/__init__.py
cudf_polars/dsl/expr.py
cudf_polars/dsl/ir.py
cudf_polars/dsl/nodebase.py
cudf_polars/dsl/to_ast.py
cudf_polars/dsl/tracing.py
cudf_polars/dsl/translate.py
cudf_polars/dsl/traversal.py
cudf_polars/dsl/expressions/__init__.py
cudf_polars/dsl/expressions/aggregation.py
cudf_polars/dsl/expressions/base.py
cudf_polars/dsl/expressions/binaryop.py
cudf_polars/dsl/expressions/boolean.py
cudf_polars/dsl/expressions/datetime.py
cudf_polars/dsl/expressions/literal.py
cudf_polars/dsl/expressions/rolling.py
cudf_polars/dsl/expressions/selection.py
cudf_polars/dsl/expressions/slicing.py
cudf_polars/dsl/expressions/sorting.py
cudf_polars/dsl/expressions/string.py
cudf_polars/dsl/expressions/struct.py
cudf_polars/dsl/expressions/ternary.py
cudf_polars/dsl/expressions/unary.py
cudf_polars/dsl/utils/__init__.py
cudf_polars/dsl/utils/aggregations.py
cudf_polars/dsl/utils/groupby.py
cudf_polars/dsl/utils/naming.py
cudf_polars/dsl/utils/replace.py
cudf_polars/dsl/utils/reshape.py
cudf_polars/dsl/utils/rolling.py
cudf_polars/dsl/utils/windows.py
cudf_polars/experimental/__init__.py
cudf_polars/experimental/base.py
cudf_polars/experimental/dask_registers.py
cudf_polars/experimental/dispatch.py
cudf_polars/experimental/distinct.py
cudf_polars/experimental/explain.py
cudf_polars/experimental/expressions.py
cudf_polars/experimental/groupby.py
cudf_polars/experimental/io.py
cudf_polars/experimental/join.py
cudf_polars/experimental/parallel.py
cudf_polars/experimental/repartition.py
cudf_polars/experimental/scheduler.py
cudf_polars/experimental/select.py
cudf_polars/experimental/shuffle.py
cudf_polars/experimental/sort.py
cudf_polars/experimental/spilling.py
cudf_polars_cu13-25.10.0.dist-info/licenses/LICENSE
cudf_polars_cu13-25.10.0.dist-info/METADATA
cudf_polars_cu13-25.10.0.dist-info/WHEEL
cudf_polars_cu13-25.10.0.dist-info/top_level.txt
cudf_polars_cu13-25.10.0.dist-info/RECORD
